plato/__init__.py
plato/client.py
plato/config.py
plato/algorithms/__init__.py
plato/algorithms/base.py
plato/algorithms/fedavg.py
plato/algorithms/fedavg_gan.py
plato/algorithms/fedavg_personalized.py
plato/algorithms/lora.py
plato/algorithms/registry.py
plato/algorithms/split_learning.py
plato/callbacks/__init__.py
plato/callbacks/client.py
plato/callbacks/handler.py
plato/callbacks/server.py
plato/callbacks/trainer.py
plato/clients/__init__.py
plato/clients/base.py
plato/clients/composable.py
plato/clients/edge.py
plato/clients/fedavg_personalized.py
plato/clients/mpc.py
plato/clients/registry.py
plato/clients/self_supervised_learning.py
plato/clients/simple.py
plato/clients/split_learning.py
plato/clients/strategies/__init__.py
plato/clients/strategies/base.py
plato/clients/strategies/defaults.py
plato/clients/strategies/edge.py
plato/clients/strategies/fedavg_personalized.py
plato/clients/strategies/mpc.py
plato/clients/strategies/split_learning.py
plato/datasources/__init__.py
plato/datasources/base.py
plato/datasources/celeba.py
plato/datasources/cifar10.py
plato/datasources/cifar100.py
plato/datasources/cinic10.py
plato/datasources/coco.py
plato/datasources/emnist.py
plato/datasources/fashion_mnist.py
plato/datasources/feature.py
plato/datasources/feature_dataset.py
plato/datasources/femnist.py
plato/datasources/flickr30k_entities.py
plato/datasources/gym.py
plato/datasources/huggingface.py
plato/datasources/kinetics.py
plato/datasources/lora.py
plato/datasources/mnist.py
plato/datasources/multimodal_base.py
plato/datasources/purchase.py
plato/datasources/qoenflx.py
plato/datasources/referitgame.py
plato/datasources/registry.py
plato/datasources/self_supervised_learning.py
plato/datasources/stl10.py
plato/datasources/texas.py
plato/datasources/tiny_imagenet.py
plato/datasources/datalib/__init__.py
plato/datasources/datalib/audio_extraction_tools.py
plato/datasources/datalib/data_utils.py
plato/datasources/datalib/flickr30kE_utils.py
plato_learn-1.41.dist-info/METADATA
plato_learn-1.41.dist-info/WHEEL
plato_learn-1.41.dist-info/licenses/LICENSE
plato_learn-1.41.dist-info/RECORD
