Metadata-Version: 2.4
Name: plato-learn
Version: 1.41
Summary: Plato: a research framework for federated learning
Project-URL: Homepage, https://github.com/TL-System/plato
Project-URL: Repository, https://github.com/TL-System/plato
Project-URL: Documentation, https://platodocs.netlify.app/
License-Expression: Apache-2.0
License-File: LICENSE
Requires-Python: >=3.13
Requires-Dist: accelerate
Requires-Dist: aiohttp
Requires-Dist: boto3
Requires-Dist: datasets
Requires-Dist: evaluate
Requires-Dist: gymnasium
Requires-Dist: kazoo
Requires-Dist: lightly
Requires-Dist: munch
Requires-Dist: numpy
Requires-Dist: opacus
Requires-Dist: peft
Requires-Dist: python-socketio
Requires-Dist: requests
Requires-Dist: tenseal
Requires-Dist: timm
Requires-Dist: torch
Requires-Dist: torch-optimizer
Requires-Dist: torchvision
Requires-Dist: transformers
Requires-Dist: zstd
